<?xml version="1.0"?>
<TextFile xmlns:xsi="http://www.w3.org/2001/XMLSchema-instance" xmlns:xsd="http://www.w3.org/2001/XMLSchema">
  <InputText>This app will allow users to provide ratings of each other's photos.</InputText>
  <Lines>
    <string>This app will allow users to provide ratings of each other's photos.</string>
  </Lines>
  <Words>
    <Word>
      <Text>This</Text>
      <LowerText>this</LowerText>
      <ProperText>This</ProperText>
      <IsSingular>false</IsSingular>
      <SingularText>This</SingularText>
      <PluralText>This</PluralText>
      <Sequence>0</Sequence>
      <PartOfSpeech>DT</PartOfSpeech>
      <Count>2</Count>
    </Word>
    <Word>
      <Text>app</Text>
      <LowerText>app</LowerText>
      <ProperText>App</ProperText>
      <IsSingular>true</IsSingular>
      <SingularText>App</SingularText>
      <PluralText>Apps</PluralText>
      <Sequence>1</Sequence>
      <PartOfSpeech>NN</PartOfSpeech>
      <Count>2</Count>
    </Word>
    <Word>
      <Text>will</Text>
      <LowerText>will</LowerText>
      <ProperText>Will</ProperText>
      <IsSingular>true</IsSingular>
      <SingularText>Will</SingularText>
      <PluralText>Wills</PluralText>
      <Sequence>2</Sequence>
      <PartOfSpeech>MD</PartOfSpeech>
      <Count>2</Count>
    </Word>
    <Word>
      <Text>allow</Text>
      <LowerText>allow</LowerText>
      <ProperText>Allow</ProperText>
      <IsSingular>true</IsSingular>
      <SingularText>Allow</SingularText>
      <PluralText>Allows</PluralText>
      <Sequence>3</Sequence>
      <PartOfSpeech>VB</PartOfSpeech>
      <Count>2</Count>
    </Word>
    <Word>
      <Text>users</Text>
      <LowerText>users</LowerText>
      <ProperText>Users</ProperText>
      <IsSingular>false</IsSingular>
      <SingularText>User</SingularText>
      <PluralText>Users</PluralText>
      <Sequence>4</Sequence>
      <PartOfSpeech>NNS</PartOfSpeech>
      <Count>2</Count>
    </Word>
    <Word>
      <Text>to</Text>
      <LowerText>to</LowerText>
      <ProperText>To</ProperText>
      <IsSingular>true</IsSingular>
      <SingularText>To</SingularText>
      <PluralText>Toes</PluralText>
      <Sequence>5</Sequence>
      <PartOfSpeech>TO</PartOfSpeech>
      <Count>2</Count>
    </Word>
    <Word>
      <Text>provide</Text>
      <LowerText>provide</LowerText>
      <ProperText>Provide</ProperText>
      <IsSingular>true</IsSingular>
      <SingularText>Provide</SingularText>
      <PluralText>Provides</PluralText>
      <Sequence>6</Sequence>
      <PartOfSpeech>VB</PartOfSpeech>
      <Count>2</Count>
    </Word>
    <Word>
      <Text>ratings</Text>
      <LowerText>ratings</LowerText>
      <ProperText>Ratings</ProperText>
      <IsSingular>false</IsSingular>
      <SingularText>Rating</SingularText>
      <PluralText>Ratings</PluralText>
      <Sequence>7</Sequence>
      <PartOfSpeech>NNS</PartOfSpeech>
      <Count>2</Count>
    </Word>
    <Word>
      <Text>of</Text>
      <LowerText>of</LowerText>
      <ProperText>Of</ProperText>
      <IsSingular>true</IsSingular>
      <SingularText>Of</SingularText>
      <PluralText>Ofs</PluralText>
      <Sequence>8</Sequence>
      <PartOfSpeech>IN</PartOfSpeech>
      <Count>2</Count>
    </Word>
    <Word>
      <Text>each</Text>
      <LowerText>each</LowerText>
      <ProperText>Each</ProperText>
      <IsSingular>false</IsSingular>
      <SingularText>Each</SingularText>
      <PluralText>Each</PluralText>
      <Sequence>9</Sequence>
      <PartOfSpeech>DT</PartOfSpeech>
      <Count>2</Count>
    </Word>
    <Word>
      <Text>other</Text>
      <LowerText>other</LowerText>
      <ProperText>Other</ProperText>
      <IsSingular>false</IsSingular>
      <SingularText>Other</SingularText>
      <PluralText>Other</PluralText>
      <Sequence>10</Sequence>
      <PartOfSpeech>JJ</PartOfSpeech>
      <Count>2</Count>
    </Word>
    <Word>
      <Text>'s</Text>
      <LowerText>'s</LowerText>
      <ProperText>'s</ProperText>
      <IsSingular>false</IsSingular>
      <SingularText>'s</SingularText>
      <PluralText>'s</PluralText>
      <Sequence>11</Sequence>
      <PartOfSpeech>POS</PartOfSpeech>
      <Count>2</Count>
    </Word>
    <Word>
      <Text>photos</Text>
      <LowerText>photos</LowerText>
      <ProperText>Photos</ProperText>
      <IsSingular>false</IsSingular>
      <SingularText>Photo</SingularText>
      <PluralText>Photos</PluralText>
      <Sequence>12</Sequence>
      <PartOfSpeech>NNS</PartOfSpeech>
      <Count>2</Count>
    </Word>
    <Word>
      <Text>.</Text>
      <LowerText>.</LowerText>
      <ProperText>.</ProperText>
      <IsSingular>false</IsSingular>
      <SingularText>.</SingularText>
      <PluralText>.</PluralText>
      <Sequence>13</Sequence>
      <PartOfSpeech>.</PartOfSpeech>
      <Count>2</Count>
    </Word>
  </Words>
  <PartsOfSpeech>
    <PartOfSpeech>
      <Code>DT</Code>
      <WordCount>0</WordCount>
      <Words>
        <Word>
          <Text>This</Text>
          <LowerText>this</LowerText>
          <ProperText>This</ProperText>
          <IsSingular>false</IsSingular>
          <SingularText>This</SingularText>
          <PluralText>This</PluralText>
          <Sequence>0</Sequence>
          <PartOfSpeech>DT</PartOfSpeech>
          <Count>2</Count>
        </Word>
        <Word>
          <Text>each</Text>
          <LowerText>each</LowerText>
          <ProperText>Each</ProperText>
          <IsSingular>false</IsSingular>
          <SingularText>Each</SingularText>
          <PluralText>Each</PluralText>
          <Sequence>9</Sequence>
          <PartOfSpeech>DT</PartOfSpeech>
          <Count>2</Count>
        </Word>
      </Words>
    </PartOfSpeech>
    <PartOfSpeech>
      <Code>NN</Code>
      <WordCount>0</WordCount>
      <Words>
        <Word>
          <Text>app</Text>
          <LowerText>app</LowerText>
          <ProperText>App</ProperText>
          <IsSingular>true</IsSingular>
          <SingularText>App</SingularText>
          <PluralText>Apps</PluralText>
          <Sequence>1</Sequence>
          <PartOfSpeech>NN</PartOfSpeech>
          <Count>2</Count>
        </Word>
      </Words>
    </PartOfSpeech>
    <PartOfSpeech>
      <Code>MD</Code>
      <WordCount>0</WordCount>
      <Words>
        <Word>
          <Text>will</Text>
          <LowerText>will</LowerText>
          <ProperText>Will</ProperText>
          <IsSingular>true</IsSingular>
          <SingularText>Will</SingularText>
          <PluralText>Wills</PluralText>
          <Sequence>2</Sequence>
          <PartOfSpeech>MD</PartOfSpeech>
          <Count>2</Count>
        </Word>
      </Words>
    </PartOfSpeech>
    <PartOfSpeech>
      <Code>VB</Code>
      <WordCount>0</WordCount>
      <Words>
        <Word>
          <Text>allow</Text>
          <LowerText>allow</LowerText>
          <ProperText>Allow</ProperText>
          <IsSingular>true</IsSingular>
          <SingularText>Allow</SingularText>
          <PluralText>Allows</PluralText>
          <Sequence>3</Sequence>
          <PartOfSpeech>VB</PartOfSpeech>
          <Count>2</Count>
        </Word>
        <Word>
          <Text>provide</Text>
          <LowerText>provide</LowerText>
          <ProperText>Provide</ProperText>
          <IsSingular>true</IsSingular>
          <SingularText>Provide</SingularText>
          <PluralText>Provides</PluralText>
          <Sequence>6</Sequence>
          <PartOfSpeech>VB</PartOfSpeech>
          <Count>2</Count>
        </Word>
      </Words>
    </PartOfSpeech>
    <PartOfSpeech>
      <Code>NNS</Code>
      <WordCount>0</WordCount>
      <Words>
        <Word>
          <Text>users</Text>
          <LowerText>users</LowerText>
          <ProperText>Users</ProperText>
          <IsSingular>false</IsSingular>
          <SingularText>User</SingularText>
          <PluralText>Users</PluralText>
          <Sequence>4</Sequence>
          <PartOfSpeech>NNS</PartOfSpeech>
          <Count>2</Count>
        </Word>
        <Word>
          <Text>ratings</Text>
          <LowerText>ratings</LowerText>
          <ProperText>Ratings</ProperText>
          <IsSingular>false</IsSingular>
          <SingularText>Rating</SingularText>
          <PluralText>Ratings</PluralText>
          <Sequence>7</Sequence>
          <PartOfSpeech>NNS</PartOfSpeech>
          <Count>2</Count>
        </Word>
        <Word>
          <Text>photos</Text>
          <LowerText>photos</LowerText>
          <ProperText>Photos</ProperText>
          <IsSingular>false</IsSingular>
          <SingularText>Photo</SingularText>
          <PluralText>Photos</PluralText>
          <Sequence>12</Sequence>
          <PartOfSpeech>NNS</PartOfSpeech>
          <Count>2</Count>
        </Word>
      </Words>
    </PartOfSpeech>
    <PartOfSpeech>
      <Code>TO</Code>
      <WordCount>0</WordCount>
      <Words>
        <Word>
          <Text>to</Text>
          <LowerText>to</LowerText>
          <ProperText>To</ProperText>
          <IsSingular>true</IsSingular>
          <SingularText>To</SingularText>
          <PluralText>Toes</PluralText>
          <Sequence>5</Sequence>
          <PartOfSpeech>TO</PartOfSpeech>
          <Count>2</Count>
        </Word>
      </Words>
    </PartOfSpeech>
    <PartOfSpeech>
      <Code>IN</Code>
      <WordCount>0</WordCount>
      <Words>
        <Word>
          <Text>of</Text>
          <LowerText>of</LowerText>
          <ProperText>Of</ProperText>
          <IsSingular>true</IsSingular>
          <SingularText>Of</SingularText>
          <PluralText>Ofs</PluralText>
          <Sequence>8</Sequence>
          <PartOfSpeech>IN</PartOfSpeech>
          <Count>2</Count>
        </Word>
      </Words>
    </PartOfSpeech>
    <PartOfSpeech>
      <Code>JJ</Code>
      <WordCount>0</WordCount>
      <Words>
        <Word>
          <Text>other</Text>
          <LowerText>other</LowerText>
          <ProperText>Other</ProperText>
          <IsSingular>false</IsSingular>
          <SingularText>Other</SingularText>
          <PluralText>Other</PluralText>
          <Sequence>10</Sequence>
          <PartOfSpeech>JJ</PartOfSpeech>
          <Count>2</Count>
        </Word>
      </Words>
    </PartOfSpeech>
    <PartOfSpeech>
      <Code>POS</Code>
      <WordCount>0</WordCount>
      <Words>
        <Word>
          <Text>'s</Text>
          <LowerText>'s</LowerText>
          <ProperText>'s</ProperText>
          <IsSingular>false</IsSingular>
          <SingularText>'s</SingularText>
          <PluralText>'s</PluralText>
          <Sequence>11</Sequence>
          <PartOfSpeech>POS</PartOfSpeech>
          <Count>2</Count>
        </Word>
      </Words>
    </PartOfSpeech>
    <PartOfSpeech>
      <Code>.</Code>
      <WordCount>0</WordCount>
      <Words>
        <Word>
          <Text>.</Text>
          <LowerText>.</LowerText>
          <ProperText>.</ProperText>
          <IsSingular>false</IsSingular>
          <SingularText>.</SingularText>
          <PluralText>.</PluralText>
          <Sequence>13</Sequence>
          <PartOfSpeech>.</PartOfSpeech>
          <Count>2</Count>
        </Word>
      </Words>
    </PartOfSpeech>
  </PartsOfSpeech>
  <Sentences>
    <Sentence>
      <Text>This app will allow users to provide ratings of each other 's photos .</Text>
      <Words>
        <Word>
          <Text>This</Text>
          <LowerText>this</LowerText>
          <ProperText>This</ProperText>
          <IsSingular>false</IsSingular>
          <SingularText>This</SingularText>
          <PluralText>This</PluralText>
          <Sequence>0</Sequence>
          <PartOfSpeech>DT</PartOfSpeech>
          <Count>2</Count>
        </Word>
        <Word>
          <Text>app</Text>
          <LowerText>app</LowerText>
          <ProperText>App</ProperText>
          <IsSingular>true</IsSingular>
          <SingularText>App</SingularText>
          <PluralText>Apps</PluralText>
          <Sequence>1</Sequence>
          <PartOfSpeech>NN</PartOfSpeech>
          <Count>2</Count>
        </Word>
        <Word>
          <Text>will</Text>
          <LowerText>will</LowerText>
          <ProperText>Will</ProperText>
          <IsSingular>true</IsSingular>
          <SingularText>Will</SingularText>
          <PluralText>Wills</PluralText>
          <Sequence>2</Sequence>
          <PartOfSpeech>MD</PartOfSpeech>
          <Count>2</Count>
        </Word>
        <Word>
          <Text>allow</Text>
          <LowerText>allow</LowerText>
          <ProperText>Allow</ProperText>
          <IsSingular>true</IsSingular>
          <SingularText>Allow</SingularText>
          <PluralText>Allows</PluralText>
          <Sequence>3</Sequence>
          <PartOfSpeech>VB</PartOfSpeech>
          <Count>2</Count>
        </Word>
        <Word>
          <Text>users</Text>
          <LowerText>users</LowerText>
          <ProperText>Users</ProperText>
          <IsSingular>false</IsSingular>
          <SingularText>User</SingularText>
          <PluralText>Users</PluralText>
          <Sequence>4</Sequence>
          <PartOfSpeech>NNS</PartOfSpeech>
          <Count>2</Count>
        </Word>
        <Word>
          <Text>to</Text>
          <LowerText>to</LowerText>
          <ProperText>To</ProperText>
          <IsSingular>true</IsSingular>
          <SingularText>To</SingularText>
          <PluralText>Toes</PluralText>
          <Sequence>5</Sequence>
          <PartOfSpeech>TO</PartOfSpeech>
          <Count>2</Count>
        </Word>
        <Word>
          <Text>provide</Text>
          <LowerText>provide</LowerText>
          <ProperText>Provide</ProperText>
          <IsSingular>true</IsSingular>
          <SingularText>Provide</SingularText>
          <PluralText>Provides</PluralText>
          <Sequence>6</Sequence>
          <PartOfSpeech>VB</PartOfSpeech>
          <Count>2</Count>
        </Word>
        <Word>
          <Text>ratings</Text>
          <LowerText>ratings</LowerText>
          <ProperText>Ratings</ProperText>
          <IsSingular>false</IsSingular>
          <SingularText>Rating</SingularText>
          <PluralText>Ratings</PluralText>
          <Sequence>7</Sequence>
          <PartOfSpeech>NNS</PartOfSpeech>
          <Count>2</Count>
        </Word>
        <Word>
          <Text>of</Text>
          <LowerText>of</LowerText>
          <ProperText>Of</ProperText>
          <IsSingular>true</IsSingular>
          <SingularText>Of</SingularText>
          <PluralText>Ofs</PluralText>
          <Sequence>8</Sequence>
          <PartOfSpeech>IN</PartOfSpeech>
          <Count>2</Count>
        </Word>
        <Word>
          <Text>each</Text>
          <LowerText>each</LowerText>
          <ProperText>Each</ProperText>
          <IsSingular>false</IsSingular>
          <SingularText>Each</SingularText>
          <PluralText>Each</PluralText>
          <Sequence>9</Sequence>
          <PartOfSpeech>DT</PartOfSpeech>
          <Count>2</Count>
        </Word>
        <Word>
          <Text>other</Text>
          <LowerText>other</LowerText>
          <ProperText>Other</ProperText>
          <IsSingular>false</IsSingular>
          <SingularText>Other</SingularText>
          <PluralText>Other</PluralText>
          <Sequence>10</Sequence>
          <PartOfSpeech>JJ</PartOfSpeech>
          <Count>2</Count>
        </Word>
        <Word>
          <Text>'s</Text>
          <LowerText>'s</LowerText>
          <ProperText>'s</ProperText>
          <IsSingular>false</IsSingular>
          <SingularText>'s</SingularText>
          <PluralText>'s</PluralText>
          <Sequence>11</Sequence>
          <PartOfSpeech>POS</PartOfSpeech>
          <Count>2</Count>
        </Word>
        <Word>
          <Text>photos</Text>
          <LowerText>photos</LowerText>
          <ProperText>Photos</ProperText>
          <IsSingular>false</IsSingular>
          <SingularText>Photo</SingularText>
          <PluralText>Photos</PluralText>
          <Sequence>12</Sequence>
          <PartOfSpeech>NNS</PartOfSpeech>
          <Count>2</Count>
        </Word>
        <Word>
          <Text>.</Text>
          <LowerText>.</LowerText>
          <ProperText>.</ProperText>
          <IsSingular>false</IsSingular>
          <SingularText>.</SingularText>
          <PluralText>.</PluralText>
          <Sequence>13</Sequence>
          <PartOfSpeech>.</PartOfSpeech>
          <Count>2</Count>
        </Word>
      </Words>
    </Sentence>
  </Sentences>
</TextFile>